helloworldflask/__init__.py
helloworldflask/main.py
helloworldflask-0.0.1.dist-info/License.txt
helloworldflask-0.0.1.dist-info/METADATA
helloworldflask-0.0.1.dist-info/WHEEL
helloworldflask-0.0.1.dist-info/top_level.txt
helloworldflask-0.0.1.dist-info/RECORD
