Metadata-Version: 2.1
Name: helloworldflask
Version: 0.0.1
Summary: UNKNOWN
Home-page: UNKNOWN
Author: Aryan Verma
Author-email: vr70aryan@gmail.com
License: MIT
Platform: UNKNOWN
Classifier: Programming Language :: Python :: 3.9
Classifier: License :: OSI Approved :: MIT License
Classifier: Operating System :: OS Independent
License-File: License.txt
